<?xml version="1.0"?>
<!--  This file conforms to the DTD xdc/cfg/configuration.dtd -->
<configuration name="ceapp/ceapp.x470MV"
    platformName="ti.platforms.evmDM6467"
    globalSection="null"
    sysStack="4096"
    stack="4096"
    heap="4096"
    argSize="512"
    execCmd="@%24%28ECHO%29%20ti.platforms.evmDM6467%20platform%20package%20cannot%20execute%20ceapp.x470MV%20on%20Linux%0A@%24%28ECHO%29%20Check%20for%20updates%20to%20this%20package%20at%3A%0A@%24%28ECHO%29%20https%3A//www-a.ti.com/downloads/sds_support/targetcontent/rtsc/index.html%0A%09%3A"
    endian="little"
    codeModel="null"
    dataModel="null">
<targets>
    <target name="gnu.targets.MVArm9"
            version="1,0,3.4,3"
            usedby="gnu.targets.rts470MV"/>
    <target name="gnu.targets.MVArm9"
            version="1,0,3.4,3"
            usedby="ti.sdo.utils.trace"/>
    <target name="gnu.targets.MVArm9"
            version="1,0,3.4,3"
            usedby="ti.sdo.ce.utils.xdm"/>
    <target name="gnu.targets.MVArm9"
            version="1,0,3.4,3"
            usedby="ti.sdo.fc.dman3"/>
    <target name="gnu.targets.MVArm9"
            version="1,0,3.4,3"
            usedby="ti.sdo.fc.acpy3"/>
    <target name="gnu.targets.MVArm9"
            version="1,0,3.4,3"
            usedby="ti.sdo.ce.alg"/>
    <target name="gnu.targets.MVArm9"
            version="1,0,3.4,3"
            usedby="ti.sdo.ce.osal.linux"/>
    <target name="gnu.targets.MVArm9"
            version="1,0,3.4,3"
            usedby="ti.sdo.ce.ipc.dsplink"/>
    <target name="gnu.targets.MVArm9"
            version="1,0,3.4,3"
            usedby="ti.sdo.ce"/>
    <target name="gnu.targets.MVArm9"
            version="1,0,3.4,3"
            usedby="ti.sdo.ce.video"/>
    <target name="gnu.targets.MVArm9"
            version="1,0,3.4,3"
            usedby="ti.sdo.ce.examples.codecs.viddec_copy"/>
    <target name="gnu.targets.MVArm9"
            version="1,0,3.4,3"
            usedby="ti.sdo.ce.examples.codecs.videnc_copy"/>
    <target name="gnu.targets.MVArm9"
            version="1,0,3.4,3"
            usedby="ti.sdo.ce.bioslog"/>
    <target name="gnu.targets.MVArm9"
            version="1,0,3.4,3"
            usedby="ti.sdo.ce.utils.trace"/>
    <target name="gnu.targets.MVArm9"
            version="1,0,3.4,3"
            usedby="ceapp"/>
</targets>
<imports>
    <package name="xdc" version="1,1,0,0,1203621209308">
    </package>
    <package name="xdc.corevers" version="16,0,0,1,1203621227324">
    </package>
    <package name="xdc.services.global" version="1,0,0,1203621258506">
        <module name="xdc.services.global.Clock"
                used="2"
                uses="">
            <feature name="enable" type="boolean" value="false"/>
        </module>
    </package>
    <package name="xdc.shelf" version="1,0,0,0,1203621283947">
    </package>
    <package name="xdc.services.spec" version="1,0,0,0,1203621302332">
    </package>
    <package name="xdc.services.intern.xsr" version="1,0,0,1203621275337">
    </package>
    <package name="xdc.services.intern.gen" version="1,0,0,0,1203621273519">
    </package>
    <package name="xdc.services.intern.cmd" version="1,0,0,0,1203621271345">
    </package>
    <package name="xdc.runtime" version="2,0,0,0,1203621258434">
        <module name="xdc.runtime.Assert"
                used="0"
                uses="">
        </module>
        <module name="xdc.runtime.Core"
                used="0"
                uses="">
        </module>
        <module name="xdc.runtime.Defaults"
                used="0"
                uses="">
        </module>
        <module name="xdc.runtime.Diags"
                used="0"
                uses="">
        </module>
        <module name="xdc.runtime.Error"
                used="0"
                uses="">
        </module>
        <module name="xdc.runtime.Gate"
                used="0"
                uses="">
        </module>
        <module name="xdc.runtime.GateNull"
                used="0"
                uses="">
        </module>
        <module name="xdc.runtime.Log"
                used="0"
                uses="">
        </module>
        <module name="xdc.runtime.LoggerBuf"
                used="0"
                uses="">
        </module>
        <module name="xdc.runtime.LoggerSys"
                used="0"
                uses="">
        </module>
        <module name="xdc.runtime.Main"
                used="0"
                uses="">
        </module>
        <module name="xdc.runtime.Memory"
                used="0"
                uses="">
        </module>
        <module name="xdc.runtime.HeapMin"
                used="0"
                uses="">
        </module>
        <module name="xdc.runtime.HeapStd"
                used="0"
                uses="">
        </module>
        <module name="xdc.runtime.Startup"
                used="0"
                uses="">
        </module>
        <module name="xdc.runtime.System"
                used="0"
                uses="">
        </module>
        <module name="xdc.runtime.SysStd"
                used="0"
                uses="">
        </module>
        <module name="xdc.runtime.SysMin"
                used="0"
                uses="">
        </module>
        <module name="xdc.runtime.Text"
                used="0"
                uses="">
        </module>
        <module name="xdc.runtime.Timestamp"
                used="0"
                uses="">
        </module>
        <module name="xdc.runtime.TimestampNull"
                used="0"
                uses="">
        </module>
        <module name="xdc.runtime.TimestampStd"
                used="0"
                uses="">
        </module>
        <module name="xdc.runtime.Types"
                used="0"
                uses="">
        </module>
    </package>
    <package name="gnu.targets.rts470MV" version="1,0,0,0,1203621000516">
    </package>
    <package name="ti.xdais.dm" version="1,0,4,1210262746529">
    </package>
    <package name="ti.xdais" version="1,2,1,1210262742149">
    </package>
    <package name="ti.sdo.utils.trace" version="1,0,0,1220943366422">
        <module name="ti.sdo.utils.trace.GT"
                used="2"
                uses="">
            <feature name="PRINTFXN" type="string" value="GTConfig_tracePrintf"/>
            <feature name="PIDFXN" type="object" value="null"/>
            <feature name="TIDFXN" type="string" value="GTConfig_threadId"/>
            <feature name="ERRORFXN" type="string" value="GTConfig_error"/>
            <feature name="MALLOCFXN" type="string" value="GTConfig_libcMalloc"/>
            <feature name="FREEFXN" type="string" value="GTConfig_libcFree"/>
            <feature name="TIMEFXN" type="string" value="GTConfig_gettimeofday"/>
            <feature name="LOCKFXN" type="string" value="GTConfig_pthreadLock"/>
            <feature name="UNLOCKFXN" type="string" value="GTConfig_pthreadUnlock"/>
            <feature name="INITFXN" type="string" value="GTConfig_posixInit"/>
            <feature name="debug" type="boolean" value="false"/>
        </module>
    </package>
    <package name="ti.sdo.ce.utils.xdm" version="1,0,1,1220951322616">
    </package>
    <package name="ti.sdo.fc.dman3" version="1,0,3,1220943053023">
        <module name="ti.sdo.fc.dman3.DMAN3"
                used="0"
                uses="">
        </module>
    </package>
    <package name="ti.sdo.fc.acpy3" version="1,0,2,1220943014135">
        <module name="ti.sdo.fc.acpy3.ACPY3"
                used="0"
                uses="">
        </module>
    </package>
    <package name="dsplink.gpp" version="3,0,0">
        <module name="dsplink.gpp.Global"
                used="0"
                uses="">
        </module>
    </package>
    <package name="ti.sdo.linuxutils.cmem" version="2,0,1,1204929560755">
        <module name="ti.sdo.linuxutils.cmem.CMEM"
                used="2"
                uses="">
            <feature name="debug" type="boolean" value="false"/>
        </module>
    </package>
    <package name="ti.catalog.c470" version="1,0,1,0,1203561761475">
        <module name="ti.catalog.c470.TMS470R10"
                used="0"
                uses="">
        </module>
        <module name="ti.catalog.c470.TMS320C5912"
                used="0"
                uses="">
        </module>
        <module name="ti.catalog.c470.TMS320C1030"
                used="0"
                uses="">
        </module>
        <module name="ti.catalog.c470.TMS320CDM6446"
                used="0"
                uses="">
        </module>
        <module name="ti.catalog.c470.TMS320CDM6467"
                used="2"
                uses="">
        </module>
        <module name="ti.catalog.c470.TMS320CDM355"
                used="0"
                uses="">
        </module>
        <module name="ti.catalog.c470.TMS320CDM510"
                used="0"
                uses="">
        </module>
        <module name="ti.catalog.c470.OMAP2430"
                used="0"
                uses="">
        </module>
        <module name="ti.catalog.c470.OMAP2431"
                used="0"
                uses="">
        </module>
        <module name="ti.catalog.c470.OMAP2530"
                used="0"
                uses="">
        </module>
        <module name="ti.catalog.c470.OMAP2531"
                used="0"
                uses="">
        </module>
        <module name="ti.catalog.c470.OMAP3403"
                used="0"
                uses="">
        </module>
        <module name="ti.catalog.c470.OMAP3405"
                used="0"
                uses="">
        </module>
        <module name="ti.catalog.c470.OMAP3503"
                used="0"
                uses="">
        </module>
        <module name="ti.catalog.c470.OMAP3515"
                used="0"
                uses="">
        </module>
        <module name="ti.catalog.c470.OMAP3425"
                used="0"
                uses="">
        </module>
        <module name="ti.catalog.c470.OMAP3525"
                used="0"
                uses="">
        </module>
        <module name="ti.catalog.c470.TMS320C3430"
                used="0"
                uses="">
        </module>
        <module name="ti.catalog.c470.OMAP3530"
                used="0"
                uses="">
        </module>
    </package>
    <package name="xdc.platform" version="1,0,1,0,1203621237157">
        <module name="xdc.platform.ExeContext"
                used="2"
                uses="">
        </module>
        <module name="xdc.platform.Utils"
                used="2"
                uses="">
        </module>
    </package>
    <package name="xdc.cfg" version="1,0,1,0,1203621225891">
        <module name="xdc.cfg.Program"
                used="2"
                uses="">
            <feature name="gen" type="xdc.cfg.Program.GenerationOptions" value="xdc.cfg.Program/gen"/>
            <feature name="globalSection" type="object" value="null"/>
            <feature name="sysStack" type="number" value="4096"/>
            <feature name="stack" type="number" value="4096"/>
            <feature name="heap" type="number" value="4096"/>
            <feature name="argSize" type="number" value="512"/>
            <feature name="execCmd" type="string" value="@%24%28ECHO%29%20ti.platforms.evmDM6467%20platform%20package%20cannot%20execute%20ceapp.x470MV%20on%20Linux%0A@%24%28ECHO%29%20Check%20for%20updates%20to%20this%20package%20at%3A%0A@%24%28ECHO%29%20https%3A//www-a.ti.com/downloads/sds_support/targetcontent/rtsc/index.html%0A%09%3A"/>
            <feature name="linkTemplate" type="object" value="null"/>
            <feature name="main" type="undefined" value="undefined"/>
            <feature name="sectMap" type="object" value="xdc.cfg.Program/sectMap"/>
            <feature name="system" type="undefined" value="undefined"/>
            <feature name="name" type="string" value="ceapp.x470MV"/>
            <feature name="endian" type="string" value="little"/>
            <feature name="codeModel" type="object" value="null"/>
            <feature name="dataModel" type="object" value="null"/>
            <feature name="build" type="object" value="%5Bobject%20Object%5D"/>
            <feature name="cpu" type="xdc.platform.IExeContext.Instance" value="%28xdc.platform.IExeContext.Instance%29xdc.platform.ExeContext.Instance%230"/>
            <feature name="platformName" type="string" value="ti.platforms.evmDM6467"/>
            <feature name="platform" type="xdc.platform.IPlatform.Instance" value="%28xdc.platform.IPlatform.Instance%29ti.platforms.evmDM6467.Platform.Instance%230"/>
            <feature name="global" type="object" value="xdc.cfg.Program/global"/>
            <feature name="symbol" type="object" value="xdc.cfg.Program/symbol"/>
            <feature name="fixedCodeAddr" type="number" value="0"/>
            <feature name="fixedDataAddr" type="number" value="0"/>
            <feature name="loadRom" type="boolean" value="false"/>
        </module>
        <module name="xdc.cfg.Main"
                used="2"
                uses="">
        </module>
    </package>
    <package name="ti.catalog.c6000" version="1,0,0,0,1203561781695">
        <module name="ti.catalog.c6000.TMS320C6452"
                used="0"
                uses="">
        </module>
        <module name="ti.catalog.c6000.TMS320CDM647"
                used="0"
                uses="">
        </module>
        <module name="ti.catalog.c6000.TMS320CDM648"
                used="0"
                uses="">
        </module>
        <module name="ti.catalog.c6000.TMS320CTNETV2685"
                used="0"
                uses="">
        </module>
        <module name="ti.catalog.c6000.TMS320C6428"
                used="0"
                uses="">
        </module>
        <module name="ti.catalog.c6000.TMS320C6711"
                used="0"
                uses="">
        </module>
        <module name="ti.catalog.c6000.TMS320C6711B"
                used="0"
                uses="">
        </module>
        <module name="ti.catalog.c6000.TMS320C6712"
                used="0"
                uses="">
        </module>
        <module name="ti.catalog.c6000.TMS320C6713"
                used="0"
                uses="">
        </module>
        <module name="ti.catalog.c6000.TMS320C6211"
                used="0"
                uses="">
        </module>
        <module name="ti.catalog.c6000.TMS320C6211B"
                used="0"
                uses="">
        </module>
        <module name="ti.catalog.c6000.TMS320C6410"
                used="0"
                uses="">
        </module>
        <module name="ti.catalog.c6000.TMS320C6411"
                used="0"
                uses="">
        </module>
        <module name="ti.catalog.c6000.TMS320C6412"
                used="0"
                uses="">
        </module>
        <module name="ti.catalog.c6000.TMS320C6413"
                used="0"
                uses="">
        </module>
        <module name="ti.catalog.c6000.TMS320C6414"
                used="0"
                uses="">
        </module>
        <module name="ti.catalog.c6000.TMS320C6415"
                used="0"
                uses="">
        </module>
        <module name="ti.catalog.c6000.TMS320C6416"
                used="0"
                uses="">
        </module>
        <module name="ti.catalog.c6000.TMS320C6418"
                used="0"
                uses="">
        </module>
        <module name="ti.catalog.c6000.TMS320C6421"
                used="0"
                uses="">
        </module>
        <module name="ti.catalog.c6000.TMS320C6424"
                used="0"
                uses="">
        </module>
        <module name="ti.catalog.c6000.TMS320CDM640"
                used="0"
                uses="">
        </module>
        <module name="ti.catalog.c6000.TMS320CDM641"
                used="0"
                uses="">
        </module>
        <module name="ti.catalog.c6000.TMS320CDM642"
                used="0"
                uses="">
        </module>
        <module name="ti.catalog.c6000.TMS320CDA700"
                used="0"
                uses="">
        </module>
        <module name="ti.catalog.c6000.TMS320CDA705"
                used="0"
                uses="">
        </module>
        <module name="ti.catalog.c6000.TMS320CDA707"
                used="0"
                uses="">
        </module>
        <module name="ti.catalog.c6000.TMS320CDA710"
                used="0"
                uses="">
        </module>
        <module name="ti.catalog.c6000.TMS320CDA700SIM"
                used="0"
                uses="">
        </module>
        <module name="ti.catalog.c6000.TMS320CDRA442"
                used="0"
                uses="">
        </module>
        <module name="ti.catalog.c6000.TMS320CDRA444"
                used="0"
                uses="">
        </module>
        <module name="ti.catalog.c6000.TMS320CDRA446"
                used="0"
                uses="">
        </module>
        <module name="ti.catalog.c6000.TMS320C6722"
                used="0"
                uses="">
        </module>
        <module name="ti.catalog.c6000.TMS320C6726"
                used="0"
                uses="">
        </module>
        <module name="ti.catalog.c6000.TMS320C6727"
                used="0"
                uses="">
        </module>
        <module name="ti.catalog.c6000.TMS320CDM415"
                used="0"
                uses="">
        </module>
        <module name="ti.catalog.c6000.TMS320CDM420"
                used="0"
                uses="">
        </module>
        <module name="ti.catalog.c6000.TMS320CDM421"
                used="0"
                uses="">
        </module>
        <module name="ti.catalog.c6000.TMS320CDM425"
                used="0"
                uses="">
        </module>
        <module name="ti.catalog.c6000.TMS320CDM426"
                used="0"
                uses="">
        </module>
        <module name="ti.catalog.c6000.TMS320CDM6431"
                used="0"
                uses="">
        </module>
        <module name="ti.catalog.c6000.TMS320CDM6433"
                used="0"
                uses="">
        </module>
        <module name="ti.catalog.c6000.TMS320CDM6435"
                used="0"
                uses="">
        </module>
        <module name="ti.catalog.c6000.TMS320CDM6437"
                used="0"
                uses="">
        </module>
        <module name="ti.catalog.c6000.TMS320CDM6441"
                used="0"
                uses="">
        </module>
        <module name="ti.catalog.c6000.TMS320CDM6443"
                used="0"
                uses="">
        </module>
        <module name="ti.catalog.c6000.TMS320CDM6446"
                used="0"
                uses="">
        </module>
        <module name="ti.catalog.c6000.TMS320CDM6467"
                used="0"
                uses="">
        </module>
        <module name="ti.catalog.c6000.TMS320CDRI300"
                used="0"
                uses="">
        </module>
        <module name="ti.catalog.c6000.TMS320CTCI6482"
                used="0"
                uses="">
        </module>
        <module name="ti.catalog.c6000.TMS320CTCI6486"
                used="0"
                uses="">
        </module>
        <module name="ti.catalog.c6000.TMS320CTCI6487"
                used="0"
                uses="">
        </module>
        <module name="ti.catalog.c6000.TMS320CTCI6488"
                used="0"
                uses="">
        </module>
        <module name="ti.catalog.c6000.TMS320CTCI6484"
                used="0"
                uses="">
        </module>
        <module name="ti.catalog.c6000.TMS320C6454"
                used="0"
                uses="">
        </module>
        <module name="ti.catalog.c6000.TMS320C6455"
                used="0"
                uses="">
        </module>
        <module name="ti.catalog.c6000.TMS320C2430"
                used="0"
                uses="">
        </module>
        <module name="ti.catalog.c6000.TMS320C3430"
                used="0"
                uses="">
        </module>
        <module name="ti.catalog.c6000.TMS320C6701"
                used="0"
                uses="">
        </module>
        <module name="ti.catalog.c6000.TMS320C6201"
                used="0"
                uses="">
        </module>
        <module name="ti.catalog.c6000.TMS320C6202"
                used="0"
                uses="">
        </module>
        <module name="ti.catalog.c6000.TMS320C6203"
                used="0"
                uses="">
        </module>
        <module name="ti.catalog.c6000.TMS320C6203B"
                used="0"
                uses="">
        </module>
        <module name="ti.catalog.c6000.TMS320C6204"
                used="0"
                uses="">
        </module>
        <module name="ti.catalog.c6000.TMS320C6205"
                used="0"
                uses="">
        </module>
        <module name="ti.catalog.c6000.TMS320CDRA406"
                used="0"
                uses="">
        </module>
        <module name="ti.catalog.c6000.TMS320CDRA402"
                used="0"
                uses="">
        </module>
        <module name="ti.catalog.c6000.TMS320CDRA404"
                used="0"
                uses="">
        </module>
        <module name="ti.catalog.c6000.TMS320CDRA414"
                used="0"
                uses="">
        </module>
        <module name="ti.catalog.c6000.TMS320CDRA416"
                used="0"
                uses="">
        </module>
        <module name="ti.catalog.c6000.TMS320CF761990"
                used="0"
                uses="">
        </module>
        <module name="ti.catalog.c6000.OMAP2431"
                used="0"
                uses="">
        </module>
        <module name="ti.catalog.c6000.OMAP2530"
                used="0"
                uses="">
        </module>
        <module name="ti.catalog.c6000.OMAP2531"
                used="0"
                uses="">
        </module>
        <module name="ti.catalog.c6000.OMAP3425"
                used="0"
                uses="">
        </module>
        <module name="ti.catalog.c6000.OMAP3525"
                used="0"
                uses="">
        </module>
        <module name="ti.catalog.c6000.OMAP3530"
                used="0"
                uses="">
        </module>
    </package>
    <package name="ti.platforms.evmDM6467" version="1,0,0,0,1192229633217">
        <module name="ti.platforms.evmDM6467.Platform"
                used="2"
                uses="">
            <feature name="BOARD" type="xdc.platform.IPlatform.Board" value="ti.platforms.evmDM6467.Platform/BOARD"/>
            <feature name="DSP" type="xdc.platform.IExeContext.Cpu" value="ti.platforms.evmDM6467.Platform/DSP"/>
            <feature name="GPP" type="xdc.platform.IExeContext.Cpu" value="ti.platforms.evmDM6467.Platform/GPP"/>
        </module>
    </package>
    <package name="ti.sdo.ce.osal" version="2,0,2,1220951127739">
        <module name="ti.sdo.ce.osal.Global"
                used="2"
                uses="">
            <feature name="DEFAULT_ARMDSPLINKCONFIG" type="ti.sdo.ce.ipc.IIpc.ArmDspLinkConfig" value="ti.sdo.ce.osal.Global/DEFAULT_ARMDSPLINKCONFIG"/>
            <feature name="os" type="ti.sdo.ce.osal.IOsal.Module" value="%28ti.sdo.ce.osal.IOsal.Module%29ti.sdo.ce.osal.linux.Settings"/>
            <feature name="armDspLinkConfig" type="ti.sdo.ce.ipc.IIpc.ArmDspLinkConfig" value="ti.sdo.ce.osal.Global/armDspLinkConfig"/>
            <feature name="runtimeEnv" type="object" value="4"/>
            <feature name="defaultMemSegId" type="object" value="null"/>
            <feature name="armCommMsgSize" type="number" value="4096"/>
            <feature name="armCommNumMsgs" type="number" value="64"/>
            <feature name="dspCommNumMsgQueues" type="number" value="64"/>
            <feature name="dspCommUseExactMatch" type="boolean" value="true"/>
            <feature name="dspConfigureMsgqAndPool" type="boolean" value="true"/>
            <feature name="dspUseMsgqAndPool" type="boolean" value="true"/>
            <feature name="dspCommMsgSize" type="number" value="1024"/>
            <feature name="dspCommNumMsgs" type="number" value="64"/>
            <feature name="usePowerManagement" type="boolean" value="false"/>
            <feature name="powerSaveMemoryBlockName" type="object" value="null"/>
            <feature name="useLinkArbiter" type="boolean" value="false"/>
            <feature name="commLocateRetries" type="number" value="20"/>
            <feature name="traceBufferSize" type="number" value="32768"/>
            <feature name="enableLogging" type="boolean" value="true"/>
            <feature name="logName" type="string" value="ti_sdo_ce_osal_LOG_Buffer"/>
            <feature name="logSize" type="number" value="256"/>
            <feature name="logType" type="string" value="circular"/>
            <feature name="logSeg" type="object" value="null"/>
            <feature name="skipVirtualAddressTranslation" type="boolean" value="false"/>
            <feature name="embedBuildInfo" type="boolean" value="true"/>
        </module>
    </package>
    <package name="ti.sdo.ce.ipc" version="2,0,1,1220951085787">
        <module name="ti.sdo.ce.ipc.Settings"
                used="2"
                uses="">
            <feature name="DEFAULT_ARMDSPLINKCONFIG" type="ti.sdo.ce.ipc.IIpc.ArmDspLinkConfig" value="ti.sdo.ce.ipc.Settings/DEFAULT_ARMDSPLINKCONFIG"/>
            <feature name="ipc" type="ti.sdo.ce.ipc.IIpc.Module" value="%28ti.sdo.ce.ipc.IIpc.Module%29ti.sdo.ce.ipc.dsplink.Ipc"/>
            <feature name="commType" type="undefined" value="undefined"/>
            <feature name="usesServer" type="boolean" value="false"/>
            <feature name="armCommMsgSize" type="number" value="4096"/>
            <feature name="armCommNumMsgs" type="number" value="64"/>
            <feature name="commLocateRetries" type="number" value="20"/>
            <feature name="useLinkArbiter" type="boolean" value="false"/>
            <feature name="dspConfigureMsgqAndPool" type="boolean" value="true"/>
            <feature name="dspUseMsgqAndPool" type="boolean" value="true"/>
            <feature name="dspCommNumMsgQueues" type="number" value="64"/>
            <feature name="dspCommUseExactMatch" type="boolean" value="true"/>
            <feature name="dspCommMsgSize" type="number" value="1024"/>
            <feature name="dspCommNumMsgs" type="number" value="64"/>
            <feature name="usePowerManagement" type="boolean" value="false"/>
            <feature name="powerSaveMemoryBlockName" type="object" value="null"/>
            <feature name="debug" type="boolean" value="false"/>
        </module>
    </package>
    <package name="ti.sdo.ce.alg" version="1,0,1,1220950781938">
        <module name="ti.sdo.ce.alg.Settings"
                used="2"
                uses="">
            <feature name="MAXGROUPID" type="number" value="20"/>
            <feature name="groupUsed" type="object" value="ti.sdo.ce.alg.Settings/groupUsed"/>
            <feature name="useIdma3" type="boolean" value="false"/>
            <feature name="useIres" type="boolean" value="false"/>
            <feature name="useHeap" type="boolean" value="false"/>
            <feature name="useCache" type="boolean" value="false"/>
            <feature name="ipcKeyBase" type="number" value="1330072641"/>
        </module>
    </package>
    <package name="ti.sdo.ce.osal.linux" version="2,0,1,1220951140072">
        <module name="ti.sdo.ce.osal.linux.Settings"
                used="2"
                uses="">
            <feature name="ipcKeyBase" type="number" value="1279349583"/>
            <feature name="maxCbListSize" type="number" value="100"/>
            <feature name="debug" type="boolean" value="false"/>
        </module>
    </package>
    <package name="ti.sdo.ce.ipc.dsplink" version="2,0,1,1220951096818">
        <module name="ti.sdo.ce.ipc.dsplink.Ipc"
                used="2"
                uses="">
            <feature name="linkConfigs" type="object" value="ti.sdo.ce.ipc.dsplink.Ipc/linkConfigs"/>
            <feature name="dspLinkCfg" type="ti.sdo.ce.ipc.dsplink.IDspLinkCfg.Module" value="%28ti.sdo.ce.ipc.dsplink.IDspLinkCfg.Module%29ti.sdo.ce.ipc.dsplink.DspLinkCfg"/>
            <feature name="armCommMsgSize" type="number" value="4096"/>
            <feature name="armCommNumMsgs" type="number" value="64"/>
            <feature name="commLocateRetries" type="number" value="20"/>
            <feature name="useLinkArbiter" type="boolean" value="false"/>
            <feature name="usePowerManagement" type="boolean" value="false"/>
            <feature name="debug" type="boolean" value="false"/>
        </module>
        <module name="ti.sdo.ce.ipc.dsplink.DspLinkCfg"
                used="2"
                uses="">
            <feature name="DEFAULT_ARMDSPLINKCONFIG" type="object" value="ti.sdo.ce.ipc.dsplink.DspLinkCfg/DEFAULT_ARMDSPLINKCONFIG"/>
        </module>
    </package>
    <package name="ti.sdo.ce" version="1,0,6,1220950771473">
        <module name="ti.sdo.ce.Engine"
                used="2"
                uses="">
            <feature name="MAXGROUPID" type="number" value="20"/>
            <feature name="local" type="ti.sdo.ce.Engine.Instance" value="ti.sdo.ce.Engine.Instance%231"/>
        </module>
        <module name="ti.sdo.ce.Server"
                used="0"
                uses="">
        </module>
        <module name="ti.sdo.ce.VISA"
                used="0"
                uses="">
        </module>
        <module name="ti.sdo.ce.CERuntime"
                used="2"
                uses="">
        </module>
        <module name="ti.sdo.ce.Settings"
                used="2"
                uses="">
            <feature name="checked" type="boolean" value="false"/>
        </module>
    </package>
    <package name="ti.sdo.ce.video" version="1,0,3,1220951334122">
        <module name="ti.sdo.ce.video.VIDENCConfig"
                used="2"
                uses="">
            <feature name="codecsList" type="object" value="%5Bobject%20Object%5D"/>
        </module>
        <module name="ti.sdo.ce.video.VIDDECConfig"
                used="2"
                uses="">
            <feature name="codecsList" type="object" value="%5Bobject%20Object%5D"/>
        </module>
    </package>
    <package name="ti.sdo.ce.examples.codecs.viddec_copy" version="">
        <module name="ti.sdo.ce.examples.codecs.viddec_copy.VIDDEC_COPY"
                used="2"
                uses="">
            <feature name="isLocal" type="boolean" value="true"/>
            <feature name="ialgFxns" type="string" value="VIDDECCOPY_TI_VIDDECCOPY"/>
            <feature name="idma3Fxns" type="undefined" value="undefined"/>
            <feature name="iresFxns" type="undefined" value="undefined"/>
            <feature name="serverFxns" type="string" value="VIDDEC_SKEL"/>
            <feature name="stubFxns" type="string" value="VIDDEC_STUBS"/>
            <feature name="rpcProtocolVersion" type="number" value="3"/>
            <feature name="uuid" type="number" value="799937622"/>
            <feature name="frameRate" type="undefined" value="undefined"/>
            <feature name="codecClassConfigurable" type="boolean" value="true"/>
            <feature name="manageInBufsCache" type="object" value="ti.sdo.ce.examples.codecs.viddec_copy.VIDDEC_COPY/manageInBufsCache"/>
            <feature name="manageOutBufsCache" type="object" value="ti.sdo.ce.examples.codecs.viddec_copy.VIDDEC_COPY/manageOutBufsCache"/>
            <feature name="manageDisplayBufsCache" type="object" value="ti.sdo.ce.examples.codecs.viddec_copy.VIDDEC_COPY/manageDisplayBufsCache"/>
        </module>
    </package>
    <package name="ti.sdo.ce.examples.codecs.videnc_copy" version="">
        <module name="ti.sdo.ce.examples.codecs.videnc_copy.VIDENC_COPY"
                used="2"
                uses="">
            <feature name="isLocal" type="boolean" value="true"/>
            <feature name="ialgFxns" type="string" value="VIDENCCOPY_TI_VIDENCCOPY"/>
            <feature name="idma3Fxns" type="object" value="null"/>
            <feature name="iresFxns" type="undefined" value="undefined"/>
            <feature name="serverFxns" type="string" value="VIDENC_SKEL"/>
            <feature name="stubFxns" type="string" value="VIDENC_STUBS"/>
            <feature name="rpcProtocolVersion" type="number" value="3"/>
            <feature name="uuid" type="number" value="781443160"/>
            <feature name="frameRate" type="undefined" value="undefined"/>
            <feature name="codecClassConfigurable" type="boolean" value="true"/>
            <feature name="manageInBufsCache" type="object" value="ti.sdo.ce.examples.codecs.videnc_copy.VIDENC_COPY/manageInBufsCache"/>
            <feature name="manageOutBufsCache" type="object" value="ti.sdo.ce.examples.codecs.videnc_copy.VIDENC_COPY/manageOutBufsCache"/>
            <feature name="manageReconBufsCache" type="object" value="ti.sdo.ce.examples.codecs.videnc_copy.VIDENC_COPY/manageReconBufsCache"/>
            <feature name="useDMA" type="boolean" value="false"/>
        </module>
    </package>
    <package name="ti.sdo.ce.bioslog" version="1,0,1,1220950800329">
        <module name="ti.sdo.ce.bioslog.LogClient"
                used="2"
                uses="">
        </module>
        <module name="ti.sdo.ce.bioslog.LogServer"
                used="0"
                uses="">
        </module>
    </package>
    <package name="ti.sdo.ce.utils.trace" version="1,0,1,1220951317087">
        <module name="ti.sdo.ce.utils.trace.TraceUtil"
                used="2"
                uses="">
            <feature name="NO_TRACING" type="ti.sdo.ce.utils.trace.TraceUtil.Attrs" value="ti.sdo.ce.utils.trace.TraceUtil/NO_TRACING"/>
            <feature name="DEFAULT_TRACING" type="ti.sdo.ce.utils.trace.TraceUtil.Attrs" value="ti.sdo.ce.utils.trace.TraceUtil/DEFAULT_TRACING"/>
            <feature name="SOCRATES_TRACING" type="ti.sdo.ce.utils.trace.TraceUtil.Attrs" value="ti.sdo.ce.utils.trace.TraceUtil/SOCRATES_TRACING"/>
            <feature name="FULL_TRACING" type="ti.sdo.ce.utils.trace.TraceUtil.Attrs" value="ti.sdo.ce.utils.trace.TraceUtil/FULL_TRACING"/>
            <feature name="attrs" type="ti.sdo.ce.utils.trace.TraceUtil.Attrs" value="ti.sdo.ce.utils.trace.TraceUtil/attrs"/>
        </module>
    </package>
    <package name="ceapp" version="">
    </package>
</imports>
</configuration>
